[
  {
    "title": "THANKS FOR BEING HERE V2 HOODIE - MIDNIGHT BLUE",
    "price": "$125.00 CAD",
    "url": "https://drmersclub.com/collections/shop-all/products/thanks-for-being-here-v2-hoodie-midnight-blue-1",
    "image_url": "https://drmersclub.com/cdn/shop/files/Artboard14_1_189b16f7-ebd6-4cff-ba81-b03b25321dec_400x.png?v=1746206986",
    "tags": [
      "hoodies",
      "main",
      "tfbh",
      "tfbhv2",
      "thanksforbeinghere",
      "tops"
    ],
    "sizes": [
      {
        "size": "XS",
        "in_stock": true
      },
      {
        "size": "S",
        "in_stock": true
      },
      {
        "size": "M",
        "in_stock": true
      },
      {
        "size": "L",
        "in_stock": true
      },
      {
        "size": "XL",
        "in_stock": true
      },
      {
        "size": "XXL",
        "in_stock": true
      },
      {
        "size": "XXXL",
        "in_stock": false
      }
    ]
  },
  {
    "title": "ESSENTIAL BOXY DOUBLE ZIP - VINTAGE BLACK",
    "price": "$135.00 CAD",
    "url": "https://drmersclub.com/collections/shop-all/products/essential-boxy-double-zip-vintage-black",
    "image_url": "https://drmersclub.com/cdn/shop/files/1_91027f16-2b18-40f5-b7d1-14b95c989a04_400x.png?v=1717178150",
    "tags": [
      "basics",
      "bfcm24",
      "capsule",
      "drmr1",
      "hoodie",
      "hoodies",
      "main",
      "may24",
      "nyconline",
      "popup",
      "reorder",
      "tops"
    ],
    "sizes": [
      {
        "size": "XS",
        "in_stock": true
      },
      {
        "size": "S",
        "in_stock": true
      },
      {
        "size": "M",
        "in_stock": true
      },
      {
        "size": "L",
        "in_stock": true
      },
      {
        "size": "XL",
        "in_stock": true
      },
      {
        "size": "XXL",
        "in_stock": false
      },
      {
        "size": "XXXL",
        "in_stock": false
      }
    ]
  },
  {
    "title": "EVERYTHING IS FINE HOODIE - CHARCOAL",
    "price": "$130.00 CAD",
    "url": "https://drmersclub.com/collections/shop-all/products/everything-is-fine-hoodie-charcoal",
    "image_url": "https://drmersclub.com/cdn/shop/files/ProductPhotosUpdated_1_400x.png?v=1709887990",
    "tags": [
      "auspringsale25",
      "bfcm24",
      "everythingisfine",
      "hoodies",
      "main",
      "reorder",
      "restock",
      "springsale25",
      "tops"
    ],
    "sizes": [
      {
        "size": "XS",
        "in_stock": false
      },
      {
        "size": "S",
        "in_stock": true
      },
      {
        "size": "M",
        "in_stock": true
      },
      {
        "size": "L",
        "in_stock": true
      },
      {
        "size": "XL",
        "in_stock": true
      },
      {
        "size": "XXL",
        "in_stock": true
      },
      {
        "size": "XXXL",
        "in_stock": true
      }
    ]
  },
  {
    "title": "VINTAGE STRIPED POLO SHIRT - SKY BLUE",
    "price": "$98.00 CAD",
    "url": "https://drmersclub.com/collections/shop-all/products/vintage-striped-polo-shirt-sky-blue",
    "image_url": "https://drmersclub.com/cdn/shop/files/78_38d36481-21ff-4e84-95c7-ac980276e9e2_400x.png?v=1717178699",
    "tags": [
      "bfcm24",
      "capsule",
      "drmr1",
      "main",
      "may24",
      "reorder",
      "top",
      "tops"
    ],
    "sizes": [
      {
        "size": "XS",
        "in_stock": false
      },
      {
        "size": "S",
        "in_stock": false
      },
      {
        "size": "M",
        "in_stock": true
      },
      {
        "size": "L",
        "in_stock": true
      },
      {
        "size": "XL",
        "in_stock": false
      },
      {
        "size": "XXL",
        "in_stock": false
      },
      {
        "size": "XXXL",
        "in_stock": false
      }
    ]
  },
  {
    "title": "CREATIVE DEPT DENIM WORK JACKET - INDIGO",
    "price": "$168.00 CAD",
    "url": "https://drmersclub.com/collections/shop-all/products/creative-dept-denim-work-jacket-indigo",
    "image_url": "https://drmersclub.com/cdn/shop/files/Artboard6-1_fea021ef-baeb-407f-a333-c32e9e6d01b1_400x.jpg?v=1743145459",
    "tags": [
      "creative+dept",
      "denim",
      "freeform",
      "jacket",
      "main",
      "tops"
    ],
    "sizes": [
      {
        "size": "XS",
        "in_stock": false
      },
      {
        "size": "S",
        "in_stock": false
      },
      {
        "size": "M",
        "in_stock": true
      },
      {
        "size": "L",
        "in_stock": true
      },
      {
        "size": "XL",
        "in_stock": true
      },
      {
        "size": "XXL",
        "in_stock": true
      },
      {
        "size": "XXXL",
        "in_stock": true
      }
    ]
  },
  {
    "title": "CREATIVE DEPT JEANS - INDIGO",
    "price": "$130.00 CAD",
    "url": "https://drmersclub.com/collections/shop-all/products/creative-dept-jeans-indigo",
    "image_url": "https://drmersclub.com/cdn/shop/files/Artboard4_1_400x.jpg?v=1743148656",
    "tags": [
      "bottoms",
      "denim",
      "freeform",
      "jeans",
      "main"
    ],
    "sizes": [
      {
        "size": "XXS+(26)",
        "in_stock": true
      },
      {
        "size": "XS+(28)",
        "in_stock": false
      },
      {
        "size": "S+(30)",
        "in_stock": true
      },
      {
        "size": "M+(32)",
        "in_stock": true
      },
      {
        "size": "L+(34)",
        "in_stock": true
      },
      {
        "size": "XL+(36)",
        "in_stock": true
      },
      {
        "size": "XXL+(38)",
        "in_stock": false
      }
    ]
  },
  {
    "title": "SMILEY LOGO KNIT - MUTED BLUE",
    "price": "$120.00 CAD",
    "url": "https://drmersclub.com/collections/shop-all/products/smiley-logo-knit-muted-blue",
    "image_url": "https://drmersclub.com/cdn/shop/files/10_400x.jpg?v=1726251344",
    "tags": [
      "bfcm24",
      "drmr1",
      "knit",
      "main",
      "smileydrop",
      "tops"
    ],
    "sizes": [
      {
        "size": "XS",
        "in_stock": false
      },
      {
        "size": "S",
        "in_stock": true
      },
      {
        "size": "M",
        "in_stock": true
      },
      {
        "size": "L",
        "in_stock": true
      },
      {
        "size": "XL",
        "in_stock": false
      },
      {
        "size": "XXL",
        "in_stock": true
      },
      {
        "size": "XXXL",
        "in_stock": false
      }
    ]
  },
  {
    "title": "LOOSE FIT JEANS - WASHED BLUE",
    "price": "$130.00 CAD",
    "url": "https://drmersclub.com/collections/shop-all/products/loose-fit-jeans-washed-blue",
    "image_url": "https://drmersclub.com/cdn/shop/files/117_400x.png?v=1717178822",
    "tags": [
      "bfcm24",
      "bottom",
      "bottoms",
      "capsule",
      "denim",
      "jeans",
      "main",
      "may24",
      "popup",
      "reorder"
    ],
    "sizes": [
      {
        "size": "XXS+(26)",
        "in_stock": false
      },
      {
        "size": "XS+(28)",
        "in_stock": true
      },
      {
        "size": "S+(30)",
        "in_stock": true
      },
      {
        "size": "M+(32)",
        "in_stock": true
      },
      {
        "size": "L+(34)",
        "in_stock": true
      },
      {
        "size": "XL+(36)",
        "in_stock": false
      },
      {
        "size": "XXL+(38)",
        "in_stock": false
      }
    ]
  },
  {
    "title": "GRAFFITI FLOWER HOODIE - MIDNIGHT BLUE",
    "price": "$130.00 CAD",
    "url": "https://drmersclub.com/collections/shop-all/products/graffiti-flower-hoodie-midnight-blue",
    "image_url": "https://drmersclub.com/cdn/shop/files/graffitiv2_400x.png?v=1743021952",
    "tags": [
      "auspringsale25",
      "hoodies",
      "main",
      "nov24",
      "nyconline",
      "springsale25",
      "tops"
    ],
    "sizes": [
      {
        "size": "XS",
        "in_stock": true
      },
      {
        "size": "S",
        "in_stock": true
      },
      {
        "size": "M",
        "in_stock": true
      },
      {
        "size": "L",
        "in_stock": true
      },
      {
        "size": "XL",
        "in_stock": true
      },
      {
        "size": "XXL",
        "in_stock": false
      },
      {
        "size": "XXXL",
        "in_stock": false
      }
    ]
  },
  {
    "title": "FALLING LETTERS ZIP UP - PURPLE DUSK",
    "price": "$148.00 CAD",
    "url": "https://drmersclub.com/collections/shop-all/products/falling-letters-zip-up-purple-dusk",
    "image_url": "https://drmersclub.com/cdn/shop/files/Artboard4_2_400x.jpg?v=1743181405",
    "tags": [
      "falling+letters",
      "freeform",
      "hoodies",
      "main",
      "tops",
      "zip+up"
    ],
    "sizes": [
      {
        "size": "XS",
        "in_stock": false
      },
      {
        "size": "S",
        "in_stock": true
      },
      {
        "size": "M",
        "in_stock": true
      },
      {
        "size": "L",
        "in_stock": true
      },
      {
        "size": "XL",
        "in_stock": true
      },
      {
        "size": "XXL",
        "in_stock": true
      },
      {
        "size": "XXXL",
        "in_stock": false
      }
    ]
  },
  {
    "title": "PERSPECTIVE HOODIE - CASTLETON GREEN",
    "price": "$120.00 CAD",
    "url": "https://drmersclub.com/collections/shop-all/products/perspective-hoodie-castleton-green",
    "image_url": "https://drmersclub.com/cdn/shop/files/11_95525580-18f6-403e-ab3b-54475b2759f0_400x.jpg?v=1694798098",
    "tags": [
      "auspringsale25",
      "bfcm24",
      "export",
      "hoodies",
      "influencer2024",
      "main",
      "perspective",
      "perspectivebirthday",
      "postspringsale",
      "reorder",
      "springsale25",
      "tops"
    ],
    "sizes": [
      {
        "size": "XS",
        "in_stock": false
      },
      {
        "size": "S",
        "in_stock": true
      },
      {
        "size": "M",
        "in_stock": true
      },
      {
        "size": "L",
        "in_stock": true
      },
      {
        "size": "XL",
        "in_stock": true
      },
      {
        "size": "XXL",
        "in_stock": true
      },
      {
        "size": "XXXL",
        "in_stock": false
      }
    ]
  },
  {
    "title": "THANKS FOR BEING HERE V2 HOODIE - BURNT FOG",
    "price": "$125.00 CAD",
    "url": "https://drmersclub.com/collections/shop-all/products/thanks-for-being-here-v2-hoodie-burnt-fog-1",
    "image_url": "https://drmersclub.com/cdn/shop/files/Artboard9_2_400x.jpg?v=1746206843",
    "tags": [
      "hoodies",
      "main",
      "tfbh",
      "tfbhv2",
      "thanksforbeinghere",
      "tops"
    ],
    "sizes": [
      {
        "size": "XS",
        "in_stock": true
      },
      {
        "size": "S",
        "in_stock": true
      },
      {
        "size": "M",
        "in_stock": true
      },
      {
        "size": "L",
        "in_stock": true
      },
      {
        "size": "XL",
        "in_stock": true
      },
      {
        "size": "XXL",
        "in_stock": true
      },
      {
        "size": "XXXL",
        "in_stock": true
      }
    ]
  },
  {
    "title": "SCRIBBLES POLO - NAVY BLUE",
    "price": "$98.00 CAD",
    "url": "https://drmersclub.com/collections/shop-all/products/scribbles-polo-navy-blue",
    "image_url": "https://drmersclub.com/cdn/shop/files/Artboard3_55900448-3c93-4326-a634-ca6d9964e627_400x.jpg?v=1743149603",
    "tags": [
      "freeform",
      "main",
      "polo",
      "scribbles",
      "tops"
    ],
    "sizes": [
      {
        "size": "XS",
        "in_stock": true
      },
      {
        "size": "S",
        "in_stock": true
      },
      {
        "size": "M",
        "in_stock": true
      },
      {
        "size": "L",
        "in_stock": true
      },
      {
        "size": "XL",
        "in_stock": true
      },
      {
        "size": "XXL",
        "in_stock": true
      }
    ]
  },
  {
    "title": "FALLING LETTERS KNIT - WASHED GREY",
    "price": "$140.00 CAD",
    "url": "https://drmersclub.com/collections/shop-all/products/falling-letters-knit-washed-grey",
    "image_url": "https://drmersclub.com/cdn/shop/files/Artboard1_4720911d-3c40-47f0-9318-0b4ed232eb80_400x.jpg?v=1743147045",
    "tags": [
      "falling+letters",
      "freeform",
      "knit",
      "knitwear",
      "main",
      "tops"
    ],
    "sizes": [
      {
        "size": "XS",
        "in_stock": true
      },
      {
        "size": "S",
        "in_stock": true
      },
      {
        "size": "M",
        "in_stock": true
      },
      {
        "size": "L",
        "in_stock": true
      },
      {
        "size": "XL",
        "in_stock": true
      },
      {
        "size": "XXL",
        "in_stock": true
      },
      {
        "size": "XXXL",
        "in_stock": true
      }
    ]
  },
  {
    "title": "SMILEY BOXY DOUBLE ZIP - ACAI",
    "price": "$140.00 CAD",
    "url": "https://drmersclub.com/collections/shop-all/products/smiley-boxy-double-zip-acai",
    "image_url": "https://drmersclub.com/cdn/shop/files/Artboard1_f487d63a-b708-4206-96f5-741adbdc509e_400x.png?v=1737917381",
    "tags": [
      "auspringsale25",
      "hoodies",
      "jan25",
      "main",
      "nyconline",
      "springsale25",
      "tops"
    ],
    "sizes": [
      {
        "size": "XS",
        "in_stock": true
      },
      {
        "size": "S",
        "in_stock": true
      },
      {
        "size": "M",
        "in_stock": true
      },
      {
        "size": "L",
        "in_stock": true
      },
      {
        "size": "XL",
        "in_stock": false
      },
      {
        "size": "XXL",
        "in_stock": true
      },
      {
        "size": "XXXL",
        "in_stock": false
      }
    ]
  },
  {
    "title": "VINTAGE BOXY HOODIE - WASHED BLACK",
    "price": "$148.00 CAD",
    "url": "https://drmersclub.com/collections/shop-all/products/vintage-boxy-hoodie-washed-black",
    "image_url": "https://drmersclub.com/cdn/shop/files/Artboard1copy7_c623d2b3-6a4a-485d-a6f0-03096cc542c2_400x.png?v=1742003775",
    "tags": [
      "basics",
      "dec24",
      "hoodies",
      "main",
      "tops",
      "vintage"
    ],
    "sizes": [
      {
        "size": "XS",
        "in_stock": true
      },
      {
        "size": "S",
        "in_stock": true
      },
      {
        "size": "M",
        "in_stock": true
      },
      {
        "size": "L",
        "in_stock": false
      },
      {
        "size": "XL",
        "in_stock": false
      },
      {
        "size": "XXL",
        "in_stock": false
      },
      {
        "size": "XXXL",
        "in_stock": false
      }
    ]
  },
  {
    "title": "THANKS FOR BEING HERE V2 HOODIE - STONE GREY",
    "price": "$125.00 CAD",
    "url": "https://drmersclub.com/collections/shop-all/products/thanks-for-being-here-v2-hoodie-stone-grey-1",
    "image_url": "https://drmersclub.com/cdn/shop/files/Artboard9-1_1_400x.png?v=1746206890",
    "tags": [
      "hoodies",
      "main",
      "tfbh",
      "tfbhv2",
      "thanksforbeinghere",
      "tops"
    ],
    "sizes": [
      {
        "size": "XS",
        "in_stock": true
      },
      {
        "size": "S",
        "in_stock": true
      },
      {
        "size": "M",
        "in_stock": true
      },
      {
        "size": "L",
        "in_stock": true
      },
      {
        "size": "XL",
        "in_stock": true
      },
      {
        "size": "XXL",
        "in_stock": true
      },
      {
        "size": "XXXL",
        "in_stock": true
      }
    ]
  },
  {
    "title": "BAGGY CARGO SWEATPANTS - CHARCOAL",
    "price": "$120.00 CAD",
    "url": "https://drmersclub.com/collections/shop-all/products/baggy-cargo-sweatpants-charcoal",
    "image_url": "https://drmersclub.com/cdn/shop/files/3_90c98bb1-d2dc-4d4a-a91f-2a17109a6c0b_400x.png?v=1742003770",
    "tags": [
      "auspringsale25",
      "bottoms",
      "feb25",
      "main",
      "springsale25",
      "sweatpants"
    ],
    "sizes": [
      {
        "size": "XS",
        "in_stock": true
      },
      {
        "size": "S",
        "in_stock": true
      },
      {
        "size": "M",
        "in_stock": true
      },
      {
        "size": "L",
        "in_stock": true
      },
      {
        "size": "XL",
        "in_stock": true
      },
      {
        "size": "XXL",
        "in_stock": true
      },
      {
        "size": "XXXL",
        "in_stock": true
      }
    ]
  },
  {
    "title": "D.R.M.E.R.S. HOODIE - BLACK",
    "price": "$125.00 CAD",
    "url": "https://drmersclub.com/collections/shop-all/products/d-r-m-e-r-s-hoodie-black",
    "image_url": "https://drmersclub.com/cdn/shop/files/Artboard8_270a252f-acdc-4fa5-aaea-e75db89b1ea0_400x.jpg?v=1738954217",
    "tags": [
      "auspringsale25",
      "feb25",
      "hoodies",
      "main",
      "springsale25",
      "tops"
    ],
    "sizes": [
      {
        "size": "XS",
        "in_stock": false
      },
      {
        "size": "S",
        "in_stock": true
      },
      {
        "size": "M",
        "in_stock": true
      },
      {
        "size": "L",
        "in_stock": true
      },
      {
        "size": "XL",
        "in_stock": true
      },
      {
        "size": "XXL",
        "in_stock": false
      },
      {
        "size": "XXXL",
        "in_stock": true
      }
    ]
  },
  {
    "title": "FREEDOM TO CREATE HOODIE - MOCHA",
    "price": "$135.00 CAD",
    "url": "https://drmersclub.com/collections/shop-all/products/freedom-to-create-hoodie-mocha-2",
    "image_url": "https://drmersclub.com/cdn/shop/files/Artboard3copy3_2c35293c-a2c0-4ea1-96b4-789034354b07_400x.jpg?v=1743183907",
    "tags": [
      "freedom+to+create",
      "freeform",
      "hoodies",
      "main",
      "tops"
    ],
    "sizes": [
      {
        "size": "XS",
        "in_stock": true
      },
      {
        "size": "S",
        "in_stock": true
      },
      {
        "size": "M",
        "in_stock": true
      },
      {
        "size": "L",
        "in_stock": true
      },
      {
        "size": "XL",
        "in_stock": true
      },
      {
        "size": "XXL",
        "in_stock": true
      },
      {
        "size": "XXXL",
        "in_stock": true
      }
    ]
  },
  {
    "title": "SCRIBBLES POLO - CREAM",
    "price": "$98.00 CAD",
    "url": "https://drmersclub.com/collections/shop-all/products/scribbles-polo-cream",
    "image_url": "https://drmersclub.com/cdn/shop/files/Artboard3-1_06ee0f35-f127-41cd-8fed-601ecad16cb0_400x.jpg?v=1743149278",
    "tags": [
      "freeform",
      "main",
      "polo",
      "scribbles",
      "tops"
    ],
    "sizes": [
      {
        "size": "XS",
        "in_stock": false
      },
      {
        "size": "S",
        "in_stock": true
      },
      {
        "size": "M",
        "in_stock": true
      },
      {
        "size": "L",
        "in_stock": true
      },
      {
        "size": "XL",
        "in_stock": true
      },
      {
        "size": "XXL",
        "in_stock": true
      }
    ]
  },
  {
    "title": "FALLING LETTERS ZIP UP - BLACK",
    "price": "$148.00 CAD",
    "url": "https://drmersclub.com/collections/shop-all/products/falling-letters-zip-up-black",
    "image_url": "https://drmersclub.com/cdn/shop/files/Artboard3_3_400x.jpg?v=1743181572",
    "tags": [
      "falling+letters",
      "freeform",
      "hoodies",
      "main",
      "tops",
      "zip+up"
    ],
    "sizes": [
      {
        "size": "XS",
        "in_stock": true
      },
      {
        "size": "S",
        "in_stock": true
      },
      {
        "size": "M",
        "in_stock": true
      },
      {
        "size": "L",
        "in_stock": true
      },
      {
        "size": "XL",
        "in_stock": true
      },
      {
        "size": "XXL",
        "in_stock": false
      },
      {
        "size": "XXXL",
        "in_stock": true
      }
    ]
  },
  {
    "title": "IF ONLY YOU KNEW HOODIE - PEBBLE",
    "price": "$105.00 CAD",
    "url": "https://drmersclub.com/collections/shop-all/products/if-only-you-knew-hoodie-pebble",
    "image_url": "https://drmersclub.com/cdn/shop/files/50_400x.png?v=1714296236",
    "tags": [
      "auspringsale25",
      "connections",
      "hoodies",
      "main",
      "reorder",
      "springsale25",
      "tops"
    ],
    "sizes": [
      {
        "size": "XS",
        "in_stock": false
      },
      {
        "size": "S",
        "in_stock": true
      },
      {
        "size": "M",
        "in_stock": true
      },
      {
        "size": "L",
        "in_stock": true
      },
      {
        "size": "XL",
        "in_stock": true
      },
      {
        "size": "XXL",
        "in_stock": false
      },
      {
        "size": "XXXL",
        "in_stock": false
      }
    ]
  },
  {
    "title": "MOTION HOODIE - SHADOW",
    "price": "$135.00 CAD",
    "url": "https://drmersclub.com/collections/shop-all/products/motion-hoodie-shadow",
    "image_url": "https://drmersclub.com/cdn/shop/files/Artboard5copy4_400x.jpg?v=1743016970",
    "tags": [
      "feb25",
      "hoodies",
      "main",
      "nyconline",
      "tops"
    ],
    "sizes": [
      {
        "size": "XS",
        "in_stock": true
      },
      {
        "size": "S",
        "in_stock": true
      },
      {
        "size": "M",
        "in_stock": true
      },
      {
        "size": "L",
        "in_stock": true
      },
      {
        "size": "XL",
        "in_stock": true
      },
      {
        "size": "XXL",
        "in_stock": false
      },
      {
        "size": "XXXL",
        "in_stock": false
      }
    ]
  },
  {
    "title": "HEART POCKET LOOSE FIT JEANS - LIGHT GREY",
    "price": "$130.00 CAD",
    "url": "https://drmersclub.com/collections/shop-all/products/heart-pocket-loose-fit-jeans-light-grey",
    "image_url": "https://drmersclub.com/cdn/shop/files/Artboard3_3d1f06ee-857d-4b17-88e4-25ae3683878b_400x.jpg?v=1743016824",
    "tags": [
      "bottom",
      "bottoms",
      "denim",
      "feb25",
      "jeans",
      "main",
      "nyconline"
    ],
    "sizes": [
      {
        "size": "XXS+(26)",
        "in_stock": false
      },
      {
        "size": "XS+(28)",
        "in_stock": false
      },
      {
        "size": "S+(30)",
        "in_stock": true
      },
      {
        "size": "M+(32)",
        "in_stock": true
      },
      {
        "size": "L+(34)",
        "in_stock": true
      },
      {
        "size": "XL+(36)",
        "in_stock": false
      },
      {
        "size": "XXL+(38)",
        "in_stock": false
      }
    ]
  },
  {
    "title": "CREATIVE DEPT JEANS - BLACK",
    "price": "$130.00 CAD",
    "url": "https://drmersclub.com/collections/shop-all/products/creative-dept-jeans-black",
    "image_url": "https://drmersclub.com/cdn/shop/files/BLKJEANSCORRECTED_400x.jpg?v=1743148757",
    "tags": [
      "bottoms",
      "denim",
      "freeform",
      "jeans",
      "main"
    ],
    "sizes": [
      {
        "size": "XXS+(26)",
        "in_stock": true
      },
      {
        "size": "XS+(28)",
        "in_stock": true
      },
      {
        "size": "S+(30)",
        "in_stock": true
      },
      {
        "size": "M+(32)",
        "in_stock": true
      },
      {
        "size": "L+(34)",
        "in_stock": true
      },
      {
        "size": "XL+(36)",
        "in_stock": true
      },
      {
        "size": "XXL+(38)",
        "in_stock": true
      }
    ]
  },
  {
    "title": "FREEDOM TO CREATE HOODIE - SOFT LILAC",
    "price": "$135.00 CAD",
    "url": "https://drmersclub.com/collections/shop-all/products/freedom-to-create-hoodie-soft-lilac-2",
    "image_url": "https://drmersclub.com/cdn/shop/files/Artboard3copy5_400x.jpg?v=1743149081",
    "tags": [
      "freedom+to+create",
      "freeform",
      "hoodies",
      "main",
      "tops"
    ],
    "sizes": [
      {
        "size": "XS",
        "in_stock": true
      },
      {
        "size": "S",
        "in_stock": true
      },
      {
        "size": "M",
        "in_stock": true
      },
      {
        "size": "L",
        "in_stock": true
      },
      {
        "size": "XL",
        "in_stock": true
      },
      {
        "size": "XXL",
        "in_stock": true
      },
      {
        "size": "XXXL",
        "in_stock": true
      }
    ]
  },
  {
    "title": "OPEN HEARTS BOXY HOODIE - CHARCOAL",
    "price": "$140.00 CAD",
    "url": "https://drmersclub.com/collections/shop-all/products/open-hearts-boxy-hoodie-charcoal",
    "image_url": "https://drmersclub.com/cdn/shop/files/9_8d83756c-ab79-44b5-a666-cd207bc1b6ae_400x.png?v=1745066083",
    "tags": [
      "auspringsale25",
      "feb25",
      "hoodies",
      "main",
      "nyconline",
      "springsale25",
      "tops"
    ],
    "sizes": [
      {
        "size": "XS",
        "in_stock": true
      },
      {
        "size": "S",
        "in_stock": true
      },
      {
        "size": "M",
        "in_stock": true
      },
      {
        "size": "L",
        "in_stock": true
      },
      {
        "size": "XL",
        "in_stock": true
      },
      {
        "size": "XXL",
        "in_stock": true
      },
      {
        "size": "XXXL",
        "in_stock": true
      }
    ]
  },
  {
    "title": "FALLING LETTERS KNIT - WASHED PURPLE",
    "price": "$140.00 CAD",
    "url": "https://drmersclub.com/collections/shop-all/products/falling-letters-knit-washed-purple",
    "image_url": "https://drmersclub.com/cdn/shop/files/Artboard1-1_7eaf0917-bd69-4cdc-8507-aefeb33768f1_400x.jpg?v=1743147134",
    "tags": [
      "falling+letters",
      "freeform",
      "knit",
      "knitwear",
      "main",
      "tops"
    ],
    "sizes": [
      {
        "size": "XS",
        "in_stock": true
      },
      {
        "size": "S",
        "in_stock": true
      },
      {
        "size": "M",
        "in_stock": true
      },
      {
        "size": "L",
        "in_stock": true
      },
      {
        "size": "XL",
        "in_stock": true
      },
      {
        "size": "XXL",
        "in_stock": true
      },
      {
        "size": "XXXL",
        "in_stock": true
      }
    ]
  },
  {
    "title": "CREATIVE DEPT DENIM WORK JACKET - BLACK",
    "price": "$168.00 CAD",
    "url": "https://drmersclub.com/collections/shop-all/products/creative-dept-denim-work-jacket-black",
    "image_url": "https://drmersclub.com/cdn/shop/files/Artboard1-1_400x.png?v=1743206688",
    "tags": [
      "denim",
      "freeform",
      "jacket",
      "main",
      "tops"
    ],
    "sizes": [
      {
        "size": "XS",
        "in_stock": false
      },
      {
        "size": "S",
        "in_stock": true
      },
      {
        "size": "M",
        "in_stock": true
      },
      {
        "size": "L",
        "in_stock": true
      },
      {
        "size": "XL",
        "in_stock": true
      },
      {
        "size": "XXL",
        "in_stock": true
      },
      {
        "size": "XXXL",
        "in_stock": true
      }
    ]
  },
  {
    "title": "CREATIVE DEPT TEE - WHITE",
    "price": "$65.00 CAD",
    "url": "https://drmersclub.com/collections/shop-all/products/creative-dept-tee-white-1",
    "image_url": "https://drmersclub.com/cdn/shop/files/Artboard2back_400x.jpg?v=1743146495",
    "tags": [
      "freeform",
      "main",
      "tee",
      "tops",
      "tshirt",
      "tshirts"
    ],
    "sizes": [
      {
        "size": "XS",
        "in_stock": true
      },
      {
        "size": "S",
        "in_stock": true
      },
      {
        "size": "M",
        "in_stock": true
      },
      {
        "size": "L",
        "in_stock": true
      },
      {
        "size": "XL",
        "in_stock": true
      },
      {
        "size": "XXL",
        "in_stock": true
      },
      {
        "size": "XXXL",
        "in_stock": true
      }
    ]
  },
  {
    "title": "CREATIVE DEPT DENIM WORK JACKET - BLUE",
    "price": "$168.00 CAD",
    "url": "https://drmersclub.com/collections/shop-all/products/creative-dept-denim-work-jacket-blue",
    "image_url": "https://drmersclub.com/cdn/shop/files/new_154de78e-36f9-457e-89d7-8dc8fb85d6d6_400x.png?v=1743205348",
    "tags": [
      "creative+dept",
      "denim",
      "freeform",
      "jacket",
      "main",
      "tops"
    ],
    "sizes": [
      {
        "size": "XS",
        "in_stock": true
      },
      {
        "size": "S",
        "in_stock": true
      },
      {
        "size": "M",
        "in_stock": true
      },
      {
        "size": "L",
        "in_stock": true
      },
      {
        "size": "XL",
        "in_stock": true
      },
      {
        "size": "XXL",
        "in_stock": true
      },
      {
        "size": "XXXL",
        "in_stock": true
      }
    ]
  },
  {
    "title": "CREATIVE DEPT JEANS - BLUE",
    "price": "$130.00 CAD",
    "url": "https://drmersclub.com/collections/shop-all/products/creative-dept-jeans-blue-yellow",
    "image_url": "https://drmersclub.com/cdn/shop/files/Artboard4copy2_400x.jpg?v=1743187510",
    "tags": [
      "bottoms",
      "denim",
      "freeform",
      "jeans",
      "main"
    ],
    "sizes": [
      {
        "size": "XXS+(26)",
        "in_stock": true
      },
      {
        "size": "XS+(28)",
        "in_stock": true
      },
      {
        "size": "S+(30)",
        "in_stock": true
      },
      {
        "size": "M+(32)",
        "in_stock": true
      },
      {
        "size": "L+(34)",
        "in_stock": true
      },
      {
        "size": "XL+(36)",
        "in_stock": true
      },
      {
        "size": "XXL+(38)",
        "in_stock": true
      }
    ]
  },
  {
    "title": "FREEDOM TO CREATE HOODIE - BASIL",
    "price": "$135.00 CAD",
    "url": "https://drmersclub.com/collections/shop-all/products/freedom-to-create-hoodie-basil-2",
    "image_url": "https://drmersclub.com/cdn/shop/files/Artboard3copy_1_400x.jpg?v=1743148836",
    "tags": [
      "freedom+to+create",
      "freeform",
      "hoodies",
      "main",
      "tops"
    ],
    "sizes": [
      {
        "size": "XS",
        "in_stock": true
      },
      {
        "size": "S",
        "in_stock": true
      },
      {
        "size": "M",
        "in_stock": true
      },
      {
        "size": "L",
        "in_stock": true
      },
      {
        "size": "XL",
        "in_stock": true
      },
      {
        "size": "XXL",
        "in_stock": true
      },
      {
        "size": "XXXL",
        "in_stock": true
      }
    ]
  },
  {
    "title": "LOOSE FIT JEANS V2 - WASHED GREY",
    "price": "$130.00 CAD",
    "url": "https://drmersclub.com/collections/shop-all/products/loose-fit-jeans-v2-washed-grey",
    "image_url": "https://drmersclub.com/cdn/shop/files/Artboard_1_copy_12_400x.png?v=1732908369",
    "tags": [
      "bottoms",
      "denim",
      "jeans",
      "main",
      "nov24",
      "nyconline"
    ],
    "sizes": [
      {
        "size": "XXS+(26)",
        "in_stock": false
      },
      {
        "size": "XS+(28)",
        "in_stock": false
      },
      {
        "size": "S+(30)",
        "in_stock": true
      },
      {
        "size": "M+(32)",
        "in_stock": true
      },
      {
        "size": "L+(34)",
        "in_stock": true
      },
      {
        "size": "XL+(36)",
        "in_stock": false
      },
      {
        "size": "XXL+(38)",
        "in_stock": false
      }
    ]
  },
  {
    "title": "ROOTS OF JOY KNIT - BEIGE",
    "price": "$125.00 CAD",
    "url": "https://drmersclub.com/collections/shop-all/products/roots-of-joy-knit-beige",
    "image_url": "https://drmersclub.com/cdn/shop/files/Artboard1copy4_e7369c67-e058-4dc7-a5b1-f906a5bda461_400x.jpg?v=1742003769",
    "tags": [
      "feb25",
      "knit",
      "main",
      "nyconline",
      "tops"
    ],
    "sizes": [
      {
        "size": "XS",
        "in_stock": false
      },
      {
        "size": "S",
        "in_stock": false
      },
      {
        "size": "M",
        "in_stock": false
      },
      {
        "size": "L",
        "in_stock": false
      },
      {
        "size": "XL",
        "in_stock": false
      },
      {
        "size": "XXL",
        "in_stock": true
      },
      {
        "size": "XXXL",
        "in_stock": true
      }
    ]
  },
  {
    "title": "CREATIVE DEPT DENIM WORK JACKET - BLACK (FRONT PRINT)",
    "price": "$158.00 CAD",
    "url": "https://drmersclub.com/collections/shop-all/products/creative-dept-denim-work-jacket-black-front-print",
    "image_url": "https://drmersclub.com/cdn/shop/files/Artboard1_5a4346bb-2d7e-4241-a432-2e05fe4505ea_400x.png?v=1743207547",
    "tags": [
      "denim",
      "freeform",
      "jacket",
      "main",
      "tops"
    ],
    "sizes": [
      {
        "size": "XS",
        "in_stock": true
      },
      {
        "size": "S",
        "in_stock": true
      },
      {
        "size": "M",
        "in_stock": true
      },
      {
        "size": "L",
        "in_stock": true
      },
      {
        "size": "XL",
        "in_stock": true
      },
      {
        "size": "XXL",
        "in_stock": true
      },
      {
        "size": "XXXL",
        "in_stock": false
      }
    ]
  },
  {
    "title": "CREATIVE DEPT DENIM WORK JACKET - BLUE (FRONT PRINT)",
    "price": "$158.00 CAD",
    "url": "https://drmersclub.com/collections/shop-all/products/creative-dept-denim-work-jacket-blue-front-print",
    "image_url": "https://drmersclub.com/cdn/shop/files/Artboard6-2_d91acd93-540b-4414-b81f-fcb028ac65ba_400x.jpg?v=1743205058",
    "tags": [
      "creative+dept",
      "denim",
      "freeform",
      "jacket",
      "main",
      "tops"
    ],
    "sizes": [
      {
        "size": "XS",
        "in_stock": true
      },
      {
        "size": "S",
        "in_stock": true
      },
      {
        "size": "M",
        "in_stock": true
      },
      {
        "size": "L",
        "in_stock": true
      },
      {
        "size": "XL",
        "in_stock": true
      },
      {
        "size": "XXL",
        "in_stock": true
      },
      {
        "size": "XXXL",
        "in_stock": true
      }
    ]
  },
  {
    "title": "LOOSE FIT JEANS - WASHED BLACK",
    "price": "$130.00 CAD",
    "url": "https://drmersclub.com/collections/shop-all/products/loose-fit-jeans-washed-black",
    "image_url": "https://drmersclub.com/cdn/shop/files/105_c566705d-f74a-4299-bfad-dbf1130ddeb7_400x.png?v=1738953031",
    "tags": [
      "bfcm24",
      "bottom",
      "bottoms",
      "capsule",
      "denim",
      "drmr1",
      "jeans",
      "main",
      "may24",
      "popup",
      "reorder"
    ],
    "sizes": [
      {
        "size": "XXS+(26)",
        "in_stock": false
      },
      {
        "size": "XS+(28)",
        "in_stock": true
      },
      {
        "size": "S+(30)",
        "in_stock": true
      },
      {
        "size": "M+(32)",
        "in_stock": true
      },
      {
        "size": "L+(34)",
        "in_stock": true
      },
      {
        "size": "XL+(36)",
        "in_stock": true
      },
      {
        "size": "XXL+(38)",
        "in_stock": true
      }
    ]
  },
  {
    "title": "ROOTS OF JOY KNIT - GRAPHITE",
    "price": "$125.00 CAD",
    "url": "https://drmersclub.com/collections/shop-all/products/roots-of-joy-knit-graphite",
    "image_url": "https://drmersclub.com/cdn/shop/files/Artboard38_d0c8c69f-8469-401d-81af-75cd748782c3_400x.jpg?v=1743017040",
    "tags": [
      "feb25",
      "knit",
      "main",
      "nyconline",
      "tops"
    ],
    "sizes": [
      {
        "size": "XS",
        "in_stock": false
      },
      {
        "size": "S",
        "in_stock": false
      },
      {
        "size": "M",
        "in_stock": false
      },
      {
        "size": "L",
        "in_stock": false
      },
      {
        "size": "XL",
        "in_stock": true
      },
      {
        "size": "XXL",
        "in_stock": true
      },
      {
        "size": "XXXL",
        "in_stock": true
      }
    ]
  },
  {
    "title": "SMILEY LOGO HOODIE - FADED BLACK",
    "price": "$120.00 CAD",
    "url": "https://drmersclub.com/collections/shop-all/products/smiley-logo-hoodie-faded-black-1",
    "image_url": "https://drmersclub.com/cdn/shop/files/32_400x.jpg?v=1726250878",
    "tags": [
      "auspringsale25",
      "bfcm24",
      "hoodie",
      "hoodies",
      "main",
      "smileydrop",
      "springsale25",
      "tops"
    ],
    "sizes": [
      {
        "size": "XS",
        "in_stock": false
      },
      {
        "size": "S",
        "in_stock": true
      },
      {
        "size": "M",
        "in_stock": true
      },
      {
        "size": "L",
        "in_stock": true
      },
      {
        "size": "XL",
        "in_stock": false
      },
      {
        "size": "XXL",
        "in_stock": false
      },
      {
        "size": "XXXL",
        "in_stock": false
      }
    ]
  },
  {
    "title": "CREATIVE DEPT DENIM WORK JACKET - INDIGO (FRONT PRINT)",
    "price": "$158.00 CAD",
    "url": "https://drmersclub.com/collections/shop-all/products/creative-dept-denim-work-jacket-indigo-front-print",
    "image_url": "https://drmersclub.com/cdn/shop/files/Artboard1-2_26ffefdd-a6e7-490f-b307-61a387693131_400x.png?v=1743208657",
    "tags": [
      "creative+dept",
      "denim",
      "freeform",
      "jacket",
      "main",
      "tops"
    ],
    "sizes": [
      {
        "size": "XS",
        "in_stock": true
      },
      {
        "size": "S",
        "in_stock": false
      },
      {
        "size": "M",
        "in_stock": true
      },
      {
        "size": "L",
        "in_stock": true
      },
      {
        "size": "XL",
        "in_stock": true
      },
      {
        "size": "XXL",
        "in_stock": true
      },
      {
        "size": "XXXL",
        "in_stock": true
      }
    ]
  },
  {
    "title": "PERSPECTIVE HOODIE - COBALT BLUE",
    "price": "$120.00 CAD",
    "url": "https://drmersclub.com/collections/shop-all/products/perspective-hoodie-cobalt-blue",
    "image_url": "https://drmersclub.com/cdn/shop/files/13_d7c357ab-ab55-494d-9cf4-945a58868774_400x.jpg?v=1694798402",
    "tags": [
      "auspringsale25",
      "bfcm24",
      "drmr1",
      "export",
      "hoodies",
      "influencer2024",
      "main",
      "perspective",
      "perspectivebirthday",
      "postspringsale",
      "reorder",
      "springsale25",
      "tops"
    ],
    "sizes": [
      {
        "size": "XS",
        "in_stock": false
      },
      {
        "size": "S",
        "in_stock": true
      },
      {
        "size": "M",
        "in_stock": true
      },
      {
        "size": "L",
        "in_stock": true
      },
      {
        "size": "XL",
        "in_stock": false
      },
      {
        "size": "XXL",
        "in_stock": true
      },
      {
        "size": "XXXL",
        "in_stock": true
      }
    ]
  },
  {
    "title": "MOTION HOODIE - POWDER PINK",
    "price": "$135.00 CAD",
    "url": "https://drmersclub.com/collections/shop-all/products/motion-hoodie-powder-pink",
    "image_url": "https://drmersclub.com/cdn/shop/files/Artboard5_c58a1637-b9cf-43b0-8a27-829155eb5758_400x.jpg?v=1743016994",
    "tags": [
      "feb25",
      "hoodies",
      "main",
      "nyconline",
      "tops"
    ],
    "sizes": [
      {
        "size": "XS",
        "in_stock": true
      },
      {
        "size": "S",
        "in_stock": true
      },
      {
        "size": "M",
        "in_stock": true
      },
      {
        "size": "L",
        "in_stock": true
      },
      {
        "size": "XL",
        "in_stock": true
      },
      {
        "size": "XXL",
        "in_stock": true
      },
      {
        "size": "XXXL",
        "in_stock": false
      }
    ]
  },
  {
    "title": "VINTAGE BOXY HOODIE - FADED PINE",
    "price": "$148.00 CAD",
    "url": "https://drmersclub.com/collections/shop-all/products/vintage-boxy-hoodie-faded-pine",
    "image_url": "https://drmersclub.com/cdn/shop/files/Artboard1copy6_400x.png?v=1735237439",
    "tags": [
      "basics",
      "dec24",
      "hoodies",
      "main",
      "nyconline",
      "tops",
      "vintage"
    ],
    "sizes": [
      {
        "size": "XS",
        "in_stock": false
      },
      {
        "size": "S",
        "in_stock": true
      },
      {
        "size": "M",
        "in_stock": false
      },
      {
        "size": "L",
        "in_stock": false
      },
      {
        "size": "XL",
        "in_stock": false
      },
      {
        "size": "XXL",
        "in_stock": false
      },
      {
        "size": "XXXL",
        "in_stock": false
      }
    ]
  },
  {
    "title": "NO PLACE LIKE HERE HOODIE - NAVY BLUE",
    "price": "$125.00 CAD",
    "url": "https://drmersclub.com/collections/shop-all/products/no-place-like-here-hoodie-navy-blue",
    "image_url": "https://drmersclub.com/cdn/shop/files/Artboard1copy5_a8fb63b8-407b-461a-8001-6f8aa440af02_400x.jpg?v=1738954405",
    "tags": [
      "feb25",
      "hoodies",
      "main",
      "tops"
    ],
    "sizes": [
      {
        "size": "XS",
        "in_stock": false
      },
      {
        "size": "S",
        "in_stock": false
      },
      {
        "size": "M",
        "in_stock": false
      },
      {
        "size": "L",
        "in_stock": false
      },
      {
        "size": "XL",
        "in_stock": false
      },
      {
        "size": "XXL",
        "in_stock": false
      },
      {
        "size": "XXXL",
        "in_stock": false
      }
    ]
  },
  {
    "title": "BAGGY CARGO PANTS - ARMY GREEN",
    "price": "$120.00 CAD",
    "url": "https://drmersclub.com/collections/shop-all/products/baggy-cargo-pants-army-green",
    "image_url": "https://drmersclub.com/cdn/shop/files/Artboard_1_copy_4_400x.png?v=1732908399",
    "tags": [
      "auspringsale25",
      "baggycargo",
      "bottoms",
      "main",
      "nov24",
      "nyconline",
      "springsale25"
    ],
    "sizes": [
      {
        "size": "XS",
        "in_stock": true
      },
      {
        "size": "S",
        "in_stock": true
      },
      {
        "size": "M",
        "in_stock": true
      },
      {
        "size": "L",
        "in_stock": true
      },
      {
        "size": "XL",
        "in_stock": true
      },
      {
        "size": "XXL",
        "in_stock": true
      },
      {
        "size": "XXXL",
        "in_stock": true
      }
    ]
  },
  {
    "title": "VINTAGE BOXY HOODIE - VIOLET",
    "price": "$148.00 CAD",
    "url": "https://drmersclub.com/collections/shop-all/products/vintage-boxy-hoodie-violet",
    "image_url": "https://drmersclub.com/cdn/shop/files/Artboard1copy5_400x.png?v=1742003774",
    "tags": [
      "basics",
      "dec24",
      "hoodies",
      "main",
      "tops",
      "vintage"
    ],
    "sizes": [
      {
        "size": "XS",
        "in_stock": false
      },
      {
        "size": "S",
        "in_stock": true
      },
      {
        "size": "M",
        "in_stock": true
      },
      {
        "size": "L",
        "in_stock": true
      },
      {
        "size": "XL",
        "in_stock": true
      },
      {
        "size": "XXL",
        "in_stock": true
      },
      {
        "size": "XXXL",
        "in_stock": false
      }
    ]
  },
  {
    "title": "SMILEY BOXY DOUBLE ZIP - CHARCOAL",
    "price": "$140.00 CAD",
    "url": "https://drmersclub.com/collections/shop-all/products/smiley-boxy-double-zip-charcoal-1",
    "image_url": "https://drmersclub.com/cdn/shop/files/6_85b6d653-b22a-406c-8bf6-f37512618832_400x.jpg?v=1737662858",
    "tags": [
      "auspringsale25",
      "bfcm24",
      "drmr1",
      "hoodie",
      "hoodies",
      "jan25",
      "main",
      "smileydrop",
      "springsale25",
      "tops",
      "zipup"
    ],
    "sizes": [
      {
        "size": "XS",
        "in_stock": false
      },
      {
        "size": "S",
        "in_stock": true
      },
      {
        "size": "M",
        "in_stock": true
      },
      {
        "size": "L",
        "in_stock": true
      },
      {
        "size": "XL",
        "in_stock": false
      },
      {
        "size": "XXL",
        "in_stock": false
      },
      {
        "size": "XXXL",
        "in_stock": true
      }
    ]
  },
  {
    "title": "BAGGY CARGO SWEATPANTS - BEIGE",
    "price": "$120.00 CAD",
    "url": "https://drmersclub.com/collections/shop-all/products/baggy-cargo-sweatpants-beige",
    "image_url": "https://drmersclub.com/cdn/shop/files/5_8b730da2-f12d-4d3d-947d-eff70ea90d74_400x.png?v=1738958448",
    "tags": [
      "auspringsale25",
      "bottoms",
      "feb25",
      "main",
      "nyconline",
      "springsale25",
      "sweatpants"
    ],
    "sizes": [
      {
        "size": "XS",
        "in_stock": true
      },
      {
        "size": "S",
        "in_stock": true
      },
      {
        "size": "M",
        "in_stock": true
      },
      {
        "size": "L",
        "in_stock": true
      },
      {
        "size": "XL",
        "in_stock": true
      },
      {
        "size": "XXL",
        "in_stock": true
      },
      {
        "size": "XXXL",
        "in_stock": true
      }
    ]
  },
  {
    "title": "MOTION HOODIE - BONE",
    "price": "$135.00 CAD",
    "url": "https://drmersclub.com/collections/shop-all/products/motion-hoodie-bone",
    "image_url": "https://drmersclub.com/cdn/shop/files/Artboard5copy2_400x.jpg?v=1743016861",
    "tags": [
      "feb25",
      "hoodies",
      "main",
      "nyconline",
      "tops"
    ],
    "sizes": [
      {
        "size": "XS",
        "in_stock": true
      },
      {
        "size": "S",
        "in_stock": true
      },
      {
        "size": "M",
        "in_stock": true
      },
      {
        "size": "L",
        "in_stock": true
      },
      {
        "size": "XL",
        "in_stock": true
      },
      {
        "size": "XXL",
        "in_stock": true
      },
      {
        "size": "XXXL",
        "in_stock": true
      }
    ]
  },
  {
    "title": "LOOSE FIT JEANS V2 - VINTAGE WASHED BLUE",
    "price": "$130.00 CAD",
    "url": "https://drmersclub.com/collections/shop-all/products/loose-fit-jeans-v2-vintage-washed-blue",
    "image_url": "https://drmersclub.com/cdn/shop/files/Artboard1copy14_400x.png?v=1742003771",
    "tags": [
      "bottoms",
      "denim",
      "jeans",
      "main",
      "nov24"
    ],
    "sizes": [
      {
        "size": "XXS+(26)",
        "in_stock": false
      },
      {
        "size": "XS+(28)",
        "in_stock": false
      },
      {
        "size": "S+(30)",
        "in_stock": false
      },
      {
        "size": "M+(32)",
        "in_stock": false
      },
      {
        "size": "L+(34)",
        "in_stock": false
      },
      {
        "size": "XL+(36)",
        "in_stock": false
      },
      {
        "size": "XXL+(38)",
        "in_stock": false
      }
    ]
  },
  {
    "title": "HEART POCKET LOOSE FIT JEANS - BLACK",
    "price": "$130.00 CAD",
    "url": "https://drmersclub.com/collections/shop-all/products/heart-pocket-loose-fit-jeans-black",
    "image_url": "https://drmersclub.com/cdn/shop/files/Artboard2_95a1388b-5142-4158-97cc-e23bdbafeb98_400x.jpg?v=1743016760",
    "tags": [
      "bottom",
      "bottoms",
      "denim",
      "feb25",
      "jeans",
      "main",
      "nyconline"
    ],
    "sizes": [
      {
        "size": "XXS+(26)",
        "in_stock": false
      },
      {
        "size": "XS+(28)",
        "in_stock": false
      },
      {
        "size": "S+(30)",
        "in_stock": true
      },
      {
        "size": "M+(32)",
        "in_stock": false
      },
      {
        "size": "L+(34)",
        "in_stock": false
      },
      {
        "size": "XL+(36)",
        "in_stock": false
      },
      {
        "size": "XXL+(38)",
        "in_stock": false
      }
    ]
  },
  {
    "title": "OPEN HEARTS BOXY HOODIE - BEIGE",
    "price": "$140.00 CAD",
    "url": "https://drmersclub.com/collections/shop-all/products/open-hearts-boxy-hoodie-beige",
    "image_url": "https://drmersclub.com/cdn/shop/files/Artboard6_1_400x.jpg?v=1745066069",
    "tags": [
      "auspringsale25",
      "feb25",
      "hoodies",
      "main",
      "nyconline",
      "springsale25",
      "tops"
    ],
    "sizes": [
      {
        "size": "XS",
        "in_stock": true
      },
      {
        "size": "S",
        "in_stock": true
      },
      {
        "size": "M",
        "in_stock": true
      },
      {
        "size": "L",
        "in_stock": true
      },
      {
        "size": "XL",
        "in_stock": true
      },
      {
        "size": "XXL",
        "in_stock": true
      },
      {
        "size": "XXXL",
        "in_stock": true
      }
    ]
  },
  {
    "title": "ROOTS OF JOY TEE - WHITE",
    "price": "$65.00 CAD",
    "url": "https://drmersclub.com/collections/shop-all/products/roots-of-joy-tee-white",
    "image_url": "https://drmersclub.com/cdn/shop/files/Artboard12_1_400x.jpg?v=1738953979",
    "tags": [
      "auspringsale25",
      "feb25",
      "main",
      "springsale25",
      "tee",
      "tops",
      "tshirt"
    ],
    "sizes": [
      {
        "size": "XS",
        "in_stock": false
      },
      {
        "size": "S",
        "in_stock": true
      },
      {
        "size": "M",
        "in_stock": true
      },
      {
        "size": "L",
        "in_stock": true
      },
      {
        "size": "XL",
        "in_stock": true
      },
      {
        "size": "XXL",
        "in_stock": true
      },
      {
        "size": "XXXL",
        "in_stock": true
      }
    ]
  },
  {
    "title": "GRAFFITI FLOWER HOODIE - LIGHT TAUPE",
    "price": "$130.00 CAD",
    "url": "https://drmersclub.com/collections/shop-all/products/graffiti-flower-hoodie-light-taupe",
    "image_url": "https://drmersclub.com/cdn/shop/files/Artboard_1_copy_2_400x.png?v=1732908188",
    "tags": [
      "auspringsale25",
      "hoodies",
      "main",
      "nov24",
      "nyconline",
      "springsale25",
      "tops"
    ],
    "sizes": [
      {
        "size": "XS",
        "in_stock": true
      },
      {
        "size": "S",
        "in_stock": true
      },
      {
        "size": "M",
        "in_stock": true
      },
      {
        "size": "L",
        "in_stock": true
      },
      {
        "size": "XL",
        "in_stock": true
      },
      {
        "size": "XXL",
        "in_stock": true
      },
      {
        "size": "XXXL",
        "in_stock": true
      }
    ]
  }
]